{
  "acousticBarrier_w_context_1.png": [
    {
      "class_name": "fixed_sound_barrier",
      "bbox_pixel": [
        156.0,
        471.0,
        1237.0,
        783.0
      ]
    }
  ],
  "acousticBarrier_w_context_4.png": [
    {
      "class_name": "fixed_sound_barrier",
      "bbox_pixel": [
        16.0,
        245.0,
        1560.0,
        945.0
      ]
    }
  ],
  "acoustic_barrier_w_context_3.jpg": [
    {
      "class_name": "portable_sound_barrier",
      "bbox_pixel": [
        119.0,
        234.0,
        1092.0,
        766.0
      ]
    }
  ],
  "acousticbarrier_1.jpeg": [
    {
      "class_name": "portable_sound_barrier",
      "bbox_pixel": [
        88.0,
        83.0,
        283.0,
        177.0
      ]
    }
  ],
  "acousticbarrier_2.jpeg": [
    {
      "class_name": "portable_sound_barrier",
      "bbox_pixel": [
        32.0,
        33.0,
        230.0,
        157.0
      ]
    }
  ],
  "acousticbarrier_3.jpg": [
    {
      "class_name": "portable_sound_barrier",
      "bbox_pixel": [
        0.0,
        176.35164835164835,
        1142.0,
        680.0
      ]
    }
  ],
  "acousticbarrier_w_context_1.jpeg": [
    {
      "class_name": "portable_sound_barrier",
      "bbox_pixel": [
        143.0,
        5.0,
        239.0,
        192.0
      ]
    },
    {
      "class_name": "fixed_sound_barrier",
      "bbox_pixel": [
        12.0,
        69.0,
        91.0,
        151.0
      ]
    }
  ],
  "measuring_tape.jpeg": [
    {
      "class_name": "measuring_tape",
      "bbox_pixel": [
        56.0,
        76.0,
        263.0,
        166.0
      ]
    }
  ],
  "measuringtape2.png": [
    {
      "class_name": "measuring_tape",
      "bbox_pixel": [
        167.0,
        128.0,
        1012.0,
        1035.0
      ]
    }
  ],
  "measuringtape_1.jpg": [
    {
      "class_name": "measuring_tape",
      "bbox_pixel": [
        242.0,
        8.0,
        1151.0,
        689.0
      ]
    }
  ],
  "measuringtape_3.jpg": [
    {
      "class_name": "measuring_tape",
      "bbox_pixel": [
        54.0,
        294.0,
        541.0,
        725.0
      ]
    },
    {
      "class_name": "measuring_tape",
      "bbox_pixel": [
        894.0,
        270.0,
        1472.0,
        735.0
      ]
    },
    {
      "class_name": "measuring_tape",
      "bbox_pixel": [
        430.74418604651163,
        275.39534883720927,
        917.7441860465115,
        706.3953488372094
      ]
    }
  ],
  "measuringtape_w_context_1.png": [
    {
      "class_name": "measuring_tape",
      "bbox_pixel": [
        878.0,
        916.0,
        1501.0,
        1041.0
      ]
    }
  ],
  "measuringtape_w_context_2.png": [
    {
      "class_name": "measuring_tape",
      "bbox_pixel": [
        0.9077669902913215,
        406.92233009708735,
        1104.5242718446602,
        698.2718446601942
      ]
    }
  ],
  "soundmeter1.png": [
    {
      "class_name": "fixed_noise_monitor",
      "bbox_pixel": [
        199.0,
        67.0,
        281.0,
        317.0
      ]
    }
  ],
  "soundmeter2.png": [
    {
      "class_name": "fixed_noise_monitor",
      "bbox_pixel": [
        412.0,
        20.0,
        776.0,
        893.0
      ]
    }
  ],
  "soundmeter3.png": [
    {
      "class_name": "fixed_noise_monitor",
      "bbox_pixel": [
        232.0,
        185.0,
        416.0,
        720.0
      ]
    }
  ],
  "soundmeter4.png": [
    {
      "class_name": "fixed_noise_monitor",
      "bbox_pixel": [
        221.17355371900828,
        103.71487603305785,
        351.7520661157025,
        641.7314049586777
      ]
    }
  ],
  "soundmeter_w_context_1.jpg": [
    {
      "class_name": "portable_sound_meter",
      "bbox_pixel": [
        586.0,
        39.0,
        608.0,
        452.0
      ]
    },
    {
      "class_name": "fixed_sound_barrier",
      "bbox_pixel": [
        56.0,
        117.0,
        276.0,
        266.0
      ]
    }
  ],
  "soundmeter_w_context_2.jpg": [
    {
      "class_name": "portable_sound_meter",
      "bbox_pixel": [
        123.0,
        102.0,
        169.0,
        229.0
      ]
    }
  ],
  "soundmeter_w_context_3.jpg": [
    {
      "class_name": "portable_sound_meter",
      "bbox_pixel": [
        80.0,
        11.0,
        142.0,
        174.0
      ]
    }
  ]
}